{
  "schemaVersion": 1,
  "id": "chathighlighter",
  "version": "${version}",
  "name": "ChatHighlighter",
  "description": "",
  "authors": [
    "uku"
  ],
  "contact": {
    "website": "https://uku3lig.net",
    "repo": "https://github.com/uku3lig/chathighlighter"
  },
  "license": "mit",
  "icon": "assets/chathighlighter/icon.png",
  "environment": "*",
  "entrypoints": {
    "main": [
      "net.uku3lig.chathighlighter.ChatHighlighter"
    ]
  },
  "mixins": [
    "chathighlighter.mixins.json"
  ],
  "depends": {
    "fabricloader": ">=0.14",
    "minecraft": "~1.19.3"
  }
}
